pytse/__init__.py
pytse/constants.py
pytse/pytse.py
pytse-1.6.2.dist-info/LICENSE
pytse-1.6.2.dist-info/METADATA
pytse-1.6.2.dist-info/WHEEL
pytse-1.6.2.dist-info/top_level.txt
pytse-1.6.2.dist-info/RECORD
