Metadata-Version: 2.1
Name: pytse
Version: 1.6.2
Summary: A small web crawler for tsetmc.com
Home-page: UNKNOWN
Author: Milad Jahromi
License: UNKNOWN
Project-URL: Source, https://github.com/miladj/PyTse
Platform: UNKNOWN
License-File: LICENSE
Requires-Dist: requests
